cfn_datadog/__init__.py
cfn_datadog/composite.py
cfn_datadog/event_alert.py
cfn_datadog/metric_alert.py
cfn_datadog/service_check.py
cfn_datadog-0.0.12.dist-info/DESCRIPTION.rst
cfn_datadog-0.0.12.dist-info/METADATA
cfn_datadog-0.0.12.dist-info/RECORD
cfn_datadog-0.0.12.dist-info/WHEEL
cfn_datadog-0.0.12.dist-info/metadata.json
cfn_datadog-0.0.12.dist-info/top_level.txt
