Metadata-Version: 2.0
Name: cfn-datadog
Version: 0.0.12
Summary: Lambda cloudformation custom resource that sets up datadog alerts
Home-page: https://github.com/nordcloud/cfn-datadog
Author: Martin Kaberg
Author-email: martin.kaberg@nordcloud.com
License: Apache Common 2.0
Platform: UNKNOWN
Requires-Dist: awacs (>=0.7.0)
Requires-Dist: boto3 (>=1.4.6)
Requires-Dist: cfn-encrypt (>=0.0.10)
Requires-Dist: cfn-response (>=0.0.4)
Requires-Dist: datadog (>=0.16.0)
Requires-Dist: troposphere (>=1.9.5)
